banner_s00zzang/__init__.py
banner_s00zzang/banner.py
banner_s00zzang-0.3.2.dist-info/METADATA
banner_s00zzang-0.3.2.dist-info/WHEEL
banner_s00zzang-0.3.2.dist-info/entry_points.txt
banner_s00zzang-0.3.2.dist-info/top_level.txt
banner_s00zzang-0.3.2.dist-info/RECORD
