Metadata-Version: 2.1
Name: banner_s00zzang
Version: 0.3.2
Summary: Default template for PDM package
Author-email: S00zzang <sujinpark8719561@gmail.com>
License: MIT
Project-URL: Homepage, https://github.com/S00zzang/banner_s00zzang
Project-URL: Issues, https://github.com/S00zzang/banner_s00zzang/issues
Requires-Python: >=3.9
Requires-Dist: pyfiglet >=1.0.2
